volleyball_prediction/__init__.py
volleyball_prediction/feature_engineering.py
volleyball_prediction/main.py
volleyball_prediction/merge_and_clean.py
volleyball_prediction/predict_api.py
volleyball_prediction/predictor.py
volleyball_prediction/train_model.py
volleyball_prediction/frontend/index.html
volleyball_prediction-0.1.101.dist-info/licenses/LICENSE
volleyball_prediction-0.1.101.dist-info/METADATA
volleyball_prediction-0.1.101.dist-info/WHEEL
volleyball_prediction-0.1.101.dist-info/top_level.txt
volleyball_prediction-0.1.101.dist-info/RECORD
