Metadata-Version: 2.4
Name: volleyball_prediction
Version: 0.1.101
Summary: Python package to predict women's volleyball match results.
Home-page: https://github.com/selinydeniz/volleyball-prediction
Author: Selinay Deniz
Author-email: İlayda & Selinay & İrem & Merve <selinydeniz@gmail.com>
License: MIT License
Project-URL: Homepage, https://github.com/selinydeniz/volleyball_prediction
Requires-Python: >=3.8
License-File: LICENSE
Requires-Dist: pandas
Requires-Dist: scikit-learn
Requires-Dist: fastapi
Requires-Dist: uvicorn[standard]
Requires-Dist: joblib
Dynamic: author
Dynamic: home-page
Dynamic: license-file
Dynamic: requires-python
